odgs/__init__.py
odgs/business_process_maps.json
odgs/cli_main.py
odgs/ontology_graph.json
odgs/physical_data_map.json
odgs/root_cause_factors.json
odgs/standard_data_rules.json
odgs/standard_dq_dimensions.json
odgs/standard_metrics.json
odgs/adapters/__init__.py
odgs/adapters/dbt/__init__.py
odgs/adapters/dbt/generate_seeds.py
odgs/adapters/dbt/generate_semantic_models.py
odgs/adapters/dbt/generate_tests.py
odgs/adapters/powerbi/__init__.py
odgs/adapters/powerbi/generate_tmsl.py
odgs/adapters/tableau/__init__.py
odgs/adapters/tableau/generate_tds.py
odgs/scripts/__init__.py
odgs/scripts/hydrate_logic.py
odgs/scripts/refactor_metrics.py
odgs/scripts/validate_schema.py
odgs-1.2.1.dist-info/licenses/LICENSE
odgs-1.2.1.dist-info/licenses/NOTICE
odgs-1.2.1.dist-info/METADATA
odgs-1.2.1.dist-info/WHEEL
odgs-1.2.1.dist-info/entry_points.txt
odgs-1.2.1.dist-info/top_level.txt
odgs-1.2.1.dist-info/RECORD
