Metadata-Version: 2.4
Name: odgs
Version: 1.2.1
Summary: The Open Data Governance Schema (ODGS) - A vendor-neutral standard for business definitions.
Author-email: Authentic Intelligence Labs <hello@authenticintelligence.labs>
License:                                  Apache License
Project-URL: Homepage, https://github.com/Authentic-Intelligence-Labs/headless-data-governance
Project-URL: Bug Tracker, https://github.com/Authentic-Intelligence-Labs/headless-data-governance/issues
Keywords: data-governance,schema,metrics,kpi,data-quality
Classifier: Programming Language :: Python :: 3
Classifier: License :: OSI Approved :: Apache Software License
Classifier: Operating System :: OS Independent
Requires-Python: >=3.7
License-File: LICENSE
License-File: NOTICE
Requires-Dist: typer[all]
Requires-Dist: rich
Requires-Dist: fastapi
Requires-Dist: uvicorn
Requires-Dist: pydantic
Dynamic: license-file
